<?xml version="1.0" encoding="utf-8"?>
<Patch>
	<Operation Class="PatchOperationSequence">
		<operations>
			<!-- Add straw as ingredient to make kibble -->
			<li Class="PatchOperationAdd">
				<xpath>/Defs/RecipeDef[defName="Make_Kibble"]/ingredients/li[2]/filter/thingDefs</xpath>
				<value>
					<li>DankPyon_Straw</li>
				</value>
			</li>
			<li Class="PatchOperationAdd">
				<xpath>/Defs/RecipeDef[defName="Make_Kibble"]/fixedIngredientFilter/thingDefs</xpath>
				<value>
					<li>DankPyon_Straw</li>
				</value>
			</li>
			<!-- Add straw from wheat harvest as a by-product -->
			<li Class="PatchOperationAdd">
				<xpath>/Defs/ThingDef[defName="DankPyon_Plant_Wheat"]</xpath>
				<value>
					<modExtensions>
						<li Class="VanillaPlantsExpanded.DualCropExtension">
							<secondaryOutput>DankPyon_Straw</secondaryOutput>
							<outPutAmount>1</outPutAmount>
						</li>
					</modExtensions>
				</value>
			</li>  
			<!-- remove DankPyon_HayRack -->
			<li Class="PatchOperationRemove">
				<xpath>Defs/ThingDef[defName = "DankPyon_HayRack"]/designationCategory</xpath>
			</li>

			<li Class="PatchOperationRemove">
				<xpath>Defs/ThingDef[defName = "DankPyon_HayRack"]/researchPrerequisites</xpath>
			</li>
			<!-- remove hay from DankPyon_CraftFlourBulk -->
			<li Class="PatchOperationReplace">
				<xpath>Defs/RecipeDef[defName = "DankPyon_CraftFlourBulk"]/products</xpath>
				<value>
					<products>
						<DankPyon_Flour>10</DankPyon_Flour>
					</products>
				</value>
			</li>
			<!-- remove hay from DankPyon_CraftFlour -->
			<li Class="PatchOperationReplace">
				<xpath>Defs/RecipeDef[defName = "DankPyon_CraftFlour"]/products</xpath>
				<value>
					<products>
						<DankPyon_Flour>1</DankPyon_Flour>
					</products>
				</value>
			</li>
		</operations>
	</Operation>
</Patch>